animegif/__init__.py
animegif/viewer.py
anime_gif_random-0.1.0.dist-info/METADATA
anime_gif_random-0.1.0.dist-info/WHEEL
anime_gif_random-0.1.0.dist-info/top_level.txt
anime_gif_random-0.1.0.dist-info/RECORD
